[
{
    "fields": {
        "alias": "navtree",
        "title": "Python.org 2015"
    },
    "model": "sitetree.tree",
    "pk": 2
},
{
    "fields": {
        "tree": 2,
        "access_restricted": false,
        "hint": "The Python Programming Language",
        "urlaspattern": true,
        "hidden": false,
        "inbreadcrumbs": true,
        "access_perm_type": 1,
        "access_loggedin": false,
        "title": "Python",
        "url": "home",
        "access_permissions": [],
        "inmenu": true,
        "insitetree": true,
        "sort_order": 110,
        "description": "",
        "alias": "python-meta",
        "access_guest": false,
        "parent": null
    },
    "model": "sitetree.treeitem",
    "pk": 110
},
{
    "fields": {
        "tree": 2,
        "access_restricted": false,
        "hint": "About Python and the Python Software Foundation",
        "urlaspattern": true,
        "hidden": false,
        "inbreadcrumbs": true,
        "access_perm_type": 1,
        "access_loggedin": false,
        "title": "About",
        "url": "about",
        "access_permissions": [],
        "inmenu": true,
        "insitetree": true,
        "sort_order": 111,
        "description": "",
        "alias": "about",
        "access_guest": false,
        "parent": 110
    },
    "model": "sitetree.treeitem",
    "pk": 111
},
{
    "fields": {
        "tree": 2,
        "access_restricted": false,
        "hint": "",
        "urlaspattern": false,
        "hidden": false,
        "inbreadcrumbs": true,
        "access_perm_type": 1,
        "access_loggedin": false,
        "title": "History / Mission",
        "url": "comingsoon",
        "access_permissions": [],
        "inmenu": true,
        "insitetree": true,
        "sort_order": 112,
        "description": "",
        "alias": null,
        "access_guest": false,
        "parent": 111
    },
    "model": "sitetree.treeitem",
    "pk": 112
},
{
    "fields": {
        "tree": 2,
        "access_restricted": false,
        "hint": "",
        "urlaspattern": false,
        "hidden": false,
        "inbreadcrumbs": true,
        "access_perm_type": 1,
        "access_loggedin": false,
        "title": "Applications",
        "url": "/about/apps/",
        "access_permissions": [],
        "inmenu": true,
        "insitetree": true,
        "sort_order": 113,
        "description": "",
        "alias": null,
        "access_guest": false,
        "parent": 111
    },
    "model": "sitetree.treeitem",
    "pk": 113
},
{
    "fields": {
        "tree": 2,
        "access_restricted": false,
        "hint": "",
        "urlaspattern": false,
        "hidden": false,
        "inbreadcrumbs": true,
        "access_perm_type": 1,
        "access_loggedin": false,
        "title": "Quotes",
        "url": "/about/quotes/",
        "access_permissions": [],
        "inmenu": true,
        "insitetree": true,
        "sort_order": 114,
        "description": "",
        "alias": null,
        "access_guest": false,
        "parent": 111
    },
    "model": "sitetree.treeitem",
    "pk": 114
},
{
    "fields": {
        "tree": 2,
        "access_restricted": false,
        "hint": "Get Started with Python",
        "urlaspattern": false,
        "hidden": false,
        "inbreadcrumbs": true,
        "access_perm_type": 1,
        "access_loggedin": false,
        "title": "Getting Started",
        "url": "/about/gettingstarted/",
        "access_permissions": [],
        "inmenu": true,
        "insitetree": true,
        "sort_order": 115,
        "description": "",
        "alias": null,
        "access_guest": false,
        "parent": 111
    },
    "model": "sitetree.treeitem",
    "pk": 115
},
{
    "fields": {
        "tree": 2,
        "access_restricted": false,
        "hint": "Get Help from the Python Community",
        "urlaspattern": false,
        "hidden": false,
        "inbreadcrumbs": true,
        "access_perm_type": 1,
        "access_loggedin": false,
        "title": "Help",
        "url": "/about/help/",
        "access_permissions": [],
        "inmenu": true,
        "insitetree": true,
        "sort_order": 116,
        "description": "",
        "alias": null,
        "access_guest": false,
        "parent": 111
    },
    "model": "sitetree.treeitem",
    "pk": 116
},
{
    "fields": {
        "tree": 2,
        "access_restricted": false,
        "hint": "Download Python software versions",
        "urlaspattern": true,
        "hidden": false,
        "inbreadcrumbs": true,
        "access_perm_type": 1,
        "access_loggedin": false,
        "title": "Downloads",
        "url": "download:download",
        "access_permissions": [],
        "inmenu": true,
        "insitetree": true,
        "sort_order": 117,
        "description": "",
        "alias": null,
        "access_guest": false,
        "parent": 110
    },
    "model": "sitetree.treeitem",
    "pk": 117
},
{
    "fields": {
        "tree": 2,
        "access_restricted": false,
        "hint": "",
        "urlaspattern": false,
        "hidden": false,
        "inbreadcrumbs": true,
        "access_perm_type": 1,
        "access_loggedin": false,
        "title": "All releases",
        "url": "download:download",
        "access_permissions": [],
        "inmenu": true,
        "insitetree": true,
        "sort_order": 118,
        "description": "",
        "alias": null,
        "access_guest": false,
        "parent": 117
    },
    "model": "sitetree.treeitem",
    "pk": 118
},
{
    "fields": {
        "tree": 2,
        "access_restricted": false,
        "hint": "",
        "urlaspattern": false,
        "hidden": false,
        "inbreadcrumbs": true,
        "access_perm_type": 1,
        "access_loggedin": false,
        "title": "Source code",
        "url": "/downloads/source/",
        "access_permissions": [],
        "inmenu": true,
        "insitetree": true,
        "sort_order": 119,
        "description": "",
        "alias": null,
        "access_guest": false,
        "parent": 117
    },
    "model": "sitetree.treeitem",
    "pk": 119
},
{
    "fields": {
        "tree": 2,
        "access_restricted": false,
        "hint": "Download Python for Windows",
        "urlaspattern": false,
        "hidden": false,
        "inbreadcrumbs": true,
        "access_perm_type": 1,
        "access_loggedin": false,
        "title": "Windows",
        "url": "/downloads/windows/",
        "access_permissions": [],
        "inmenu": true,
        "insitetree": true,
        "sort_order": 120,
        "description": "",
        "alias": null,
        "access_guest": false,
        "parent": 117
    },
    "model": "sitetree.treeitem",
    "pk": 120
},
{
    "fields": {
        "tree": 2,
        "access_restricted": false,
        "hint": "Download Python for Mac OSX",
        "urlaspattern": false,
        "hidden": false,
        "inbreadcrumbs": true,
        "access_perm_type": 1,
        "access_loggedin": false,
        "title": "Mac OSX",
        "url": "/downloads/mac-osx/",
        "access_permissions": [],
        "inmenu": true,
        "insitetree": true,
        "sort_order": 121,
        "description": "",
        "alias": null,
        "access_guest": false,
        "parent": 117
    },
    "model": "sitetree.treeitem",
    "pk": 121
},
{
    "fields": {
        "tree": 2,
        "access_restricted": false,
        "hint": "Download Python for other platforms",
        "urlaspattern": false,
        "hidden": false,
        "inbreadcrumbs": true,
        "access_perm_type": 1,
        "access_loggedin": false,
        "title": "Other Platforms",
        "url": "/download/other/",
        "access_permissions": [],
        "inmenu": true,
        "insitetree": true,
        "sort_order": 122,
        "description": "",
        "alias": null,
        "access_guest": false,
        "parent": 117
    },
    "model": "sitetree.treeitem",
    "pk": 122
},
{
    "fields": {
        "tree": 2,
        "access_restricted": false,
        "hint": "",
        "urlaspattern": false,
        "hidden": false,
        "inbreadcrumbs": true,
        "access_perm_type": 1,
        "access_loggedin": false,
        "title": "License",
        "url": "https://docs.python.org/3/license.html",
        "access_permissions": [],
        "inmenu": true,
        "insitetree": true,
        "sort_order": 123,
        "description": "",
        "alias": null,
        "access_guest": false,
        "parent": 117
    },
    "model": "sitetree.treeitem",
    "pk": 123
},
{
    "fields": {
        "tree": 2,
        "access_restricted": false,
        "hint": "Other Python implementations",
        "urlaspattern": false,
        "hidden": false,
        "inbreadcrumbs": true,
        "access_perm_type": 1,
        "access_loggedin": false,
        "title": "Alternative Implementations",
        "url": "/download/alternatives",
        "access_permissions": [],
        "inmenu": true,
        "insitetree": true,
        "sort_order": 124,
        "description": "",
        "alias": null,
        "access_guest": false,
        "parent": 117
    },
    "model": "sitetree.treeitem",
    "pk": 124
},
{
    "fields": {
        "tree": 2,
        "access_restricted": false,
        "hint": "",
        "urlaspattern": true,
        "hidden": false,
        "inbreadcrumbs": true,
        "access_perm_type": 1,
        "access_loggedin": false,
        "title": "Documentation",
        "url": "documentation",
        "access_permissions": [],
        "inmenu": true,
        "insitetree": true,
        "sort_order": 125,
        "description": "",
        "alias": null,
        "access_guest": false,
        "parent": 110
    },
    "model": "sitetree.treeitem",
    "pk": 125
},
{
    "fields": {
        "tree": 2,
        "access_restricted": false,
        "hint": "",
        "urlaspattern": true,
        "hidden": false,
        "inbreadcrumbs": true,
        "access_perm_type": 1,
        "access_loggedin": false,
        "title": "Docs",
        "url": "documentation",
        "access_permissions": [],
        "inmenu": true,
        "insitetree": true,
        "sort_order": 126,
        "description": "",
        "alias": null,
        "access_guest": false,
        "parent": 125
    },
    "model": "sitetree.treeitem",
    "pk": 126
},
{
    "fields": {
        "tree": 2,
        "access_restricted": false,
        "hint": "",
        "urlaspattern": false,
        "hidden": false,
        "inbreadcrumbs": true,
        "access_perm_type": 1,
        "access_loggedin": false,
        "title": "Audio/Visual Talks",
        "url": "/doc/av",
        "access_permissions": [],
        "inmenu": true,
        "insitetree": true,
        "sort_order": 127,
        "description": "",
        "alias": null,
        "access_guest": false,
        "parent": 125
    },
    "model": "sitetree.treeitem",
    "pk": 127
},
{
    "fields": {
        "tree": 2,
        "access_restricted": false,
        "hint": "",
        "urlaspattern": false,
        "hidden": false,
        "inbreadcrumbs": true,
        "access_perm_type": 1,
        "access_loggedin": false,
        "title": "Beginner's Guide",
        "url": "https://wiki.python.org/moin/BeginnersGuide",
        "access_permissions": [],
        "inmenu": true,
        "insitetree": true,
        "sort_order": 128,
        "description": "",
        "alias": null,
        "access_guest": false,
        "parent": 125
    },
    "model": "sitetree.treeitem",
    "pk": 128
},
{
    "fields": {
        "tree": 2,
        "access_restricted": false,
        "hint": "",
        "urlaspattern": false,
        "hidden": false,
        "inbreadcrumbs": true,
        "access_perm_type": 1,
        "access_loggedin": false,
        "title": "Developer's Guide",
        "url": "https://docs.python.org/devguide/",
        "access_permissions": [],
        "inmenu": true,
        "insitetree": true,
        "sort_order": 129,
        "description": "",
        "alias": null,
        "access_guest": false,
        "parent": 125
    },
    "model": "sitetree.treeitem",
    "pk": 129
},
{
    "fields": {
        "tree": 2,
        "access_restricted": false,
        "hint": "",
        "urlaspattern": false,
        "hidden": false,
        "inbreadcrumbs": true,
        "access_perm_type": 1,
        "access_loggedin": false,
        "title": "FAQ",
        "url": "https://docs.python.org/faq/",
        "access_permissions": [],
        "inmenu": true,
        "insitetree": true,
        "sort_order": 130,
        "description": "",
        "alias": null,
        "access_guest": false,
        "parent": 125
    },
    "model": "sitetree.treeitem",
    "pk": 130
},
{
    "fields": {
        "tree": 2,
        "access_restricted": false,
        "hint": "",
        "urlaspattern": false,
        "hidden": false,
        "inbreadcrumbs": true,
        "access_perm_type": 1,
        "access_loggedin": false,
        "title": "Non-English Docs",
        "url": "http://wiki.python.org/moin/Languages",
        "access_permissions": [],
        "inmenu": true,
        "insitetree": true,
        "sort_order": 131,
        "description": "",
        "alias": null,
        "access_guest": false,
        "parent": 125
    },
    "model": "sitetree.treeitem",
    "pk": 131
},
{
    "fields": {
        "tree": 2,
        "access_restricted": false,
        "hint": "",
        "urlaspattern": false,
        "hidden": false,
        "inbreadcrumbs": true,
        "access_perm_type": 1,
        "access_loggedin": false,
        "title": "PEP Index",
        "url": "http://python.org/dev/peps/",
        "access_permissions": [],
        "inmenu": true,
        "insitetree": true,
        "sort_order": 132,
        "description": "",
        "alias": null,
        "access_guest": false,
        "parent": 125
    },
    "model": "sitetree.treeitem",
    "pk": 132
},
{
    "fields": {
        "tree": 2,
        "access_restricted": false,
        "hint": "",
        "urlaspattern": false,
        "hidden": false,
        "inbreadcrumbs": true,
        "access_perm_type": 1,
        "access_loggedin": false,
        "title": "Python Books",
        "url": "https://wiki.python.org/moin/PythonBooks",
        "access_permissions": [],
        "inmenu": true,
        "insitetree": true,
        "sort_order": 133,
        "description": "",
        "alias": null,
        "access_guest": false,
        "parent": 125
    },
    "model": "sitetree.treeitem",
    "pk": 133
},
{
    "fields": {
        "tree": 2,
        "access_restricted": false,
        "hint": "",
        "urlaspattern": false,
        "hidden": false,
        "inbreadcrumbs": true,
        "access_perm_type": 1,
        "access_loggedin": false,
        "title": "Success Stories",
        "url": "/about/success/",
        "access_permissions": [],
        "inmenu": true,
        "insitetree": true,
        "sort_order": 134,
        "description": "",
        "alias": null,
        "access_guest": false,
        "parent": 110
    },
    "model": "sitetree.treeitem",
    "pk": 134
},
{
    "fields": {
        "tree": 2,
        "access_restricted": false,
        "hint": "",
        "urlaspattern": false,
        "hidden": false,
        "inbreadcrumbs": true,
        "access_perm_type": 1,
        "access_loggedin": false,
        "title": "Arts",
        "url": "/about/success/#arts",
        "access_permissions": [],
        "inmenu": true,
        "insitetree": true,
        "sort_order": 135,
        "description": "",
        "alias": null,
        "access_guest": false,
        "parent": 134
    },
    "model": "sitetree.treeitem",
    "pk": 135
},
{
    "fields": {
        "tree": 2,
        "access_restricted": false,
        "hint": "",
        "urlaspattern": false,
        "hidden": false,
        "inbreadcrumbs": true,
        "access_perm_type": 1,
        "access_loggedin": false,
        "title": "Business",
        "url": "/about/success/#business",
        "access_permissions": [],
        "inmenu": true,
        "insitetree": true,
        "sort_order": 136,
        "description": "",
        "alias": null,
        "access_guest": false,
        "parent": 134
    },
    "model": "sitetree.treeitem",
    "pk": 136
},
{
    "fields": {
        "tree": 2,
        "access_restricted": false,
        "hint": "",
        "urlaspattern": false,
        "hidden": false,
        "inbreadcrumbs": true,
        "access_perm_type": 1,
        "access_loggedin": false,
        "title": "Education",
        "url": "/about/success/#education",
        "access_permissions": [],
        "inmenu": true,
        "insitetree": true,
        "sort_order": 137,
        "description": "",
        "alias": null,
        "access_guest": false,
        "parent": 134
    },
    "model": "sitetree.treeitem",
    "pk": 137
},
{
    "fields": {
        "tree": 2,
        "access_restricted": false,
        "hint": "",
        "urlaspattern": false,
        "hidden": false,
        "inbreadcrumbs": true,
        "access_perm_type": 1,
        "access_loggedin": false,
        "title": "Engineering",
        "url": "/about/success/#engineering",
        "access_permissions": [],
        "inmenu": true,
        "insitetree": true,
        "sort_order": 138,
        "description": "",
        "alias": null,
        "access_guest": false,
        "parent": 134
    },
    "model": "sitetree.treeitem",
    "pk": 138
},
{
    "fields": {
        "tree": 2,
        "access_restricted": false,
        "hint": "",
        "urlaspattern": false,
        "hidden": false,
        "inbreadcrumbs": true,
        "access_perm_type": 1,
        "access_loggedin": false,
        "title": "Government",
        "url": "/about/success/#government",
        "access_permissions": [],
        "inmenu": true,
        "insitetree": true,
        "sort_order": 139,
        "description": "",
        "alias": null,
        "access_guest": false,
        "parent": 134
    },
    "model": "sitetree.treeitem",
    "pk": 139
},
{
    "fields": {
        "tree": 2,
        "access_restricted": false,
        "hint": "",
        "urlaspattern": false,
        "hidden": false,
        "inbreadcrumbs": true,
        "access_perm_type": 1,
        "access_loggedin": false,
        "title": "Scientific",
        "url": "/about/success/#scientific",
        "access_permissions": [],
        "inmenu": true,
        "insitetree": true,
        "sort_order": 140,
        "description": "",
        "alias": null,
        "access_guest": false,
        "parent": 134
    },
    "model": "sitetree.treeitem",
    "pk": 140
},
{
    "fields": {
        "tree": 2,
        "access_restricted": false,
        "hint": "",
        "urlaspattern": false,
        "hidden": false,
        "inbreadcrumbs": true,
        "access_perm_type": 1,
        "access_loggedin": false,
        "title": "Software Development",
        "url": "/about/success/#software-development",
        "access_permissions": [],
        "inmenu": true,
        "insitetree": true,
        "sort_order": 141,
        "description": "",
        "alias": null,
        "access_guest": false,
        "parent": 134
    },
    "model": "sitetree.treeitem",
    "pk": 141
},
{
    "fields": {
        "tree": 2,
        "access_restricted": false,
        "hint": "",
        "urlaspattern": true,
        "hidden": false,
        "inbreadcrumbs": true,
        "access_perm_type": 1,
        "access_loggedin": false,
        "title": "News",
        "url": "blog",
        "access_permissions": [],
        "inmenu": true,
        "insitetree": true,
        "sort_order": 142,
        "description": "",
        "alias": null,
        "access_guest": false,
        "parent": 110
    },
    "model": "sitetree.treeitem",
    "pk": 142
},
{
    "fields": {
        "tree": 2,
        "access_restricted": false,
        "hint": "",
        "urlaspattern": false,
        "hidden": false,
        "inbreadcrumbs": true,
        "access_perm_type": 1,
        "access_loggedin": false,
        "title": "Python News",
        "url": "blog",
        "access_permissions": [],
        "inmenu": true,
        "insitetree": true,
        "sort_order": 143,
        "description": "",
        "alias": null,
        "access_guest": false,
        "parent": 142
    },
    "model": "sitetree.treeitem",
    "pk": 143
},
{
    "fields": {
        "tree": 2,
        "access_restricted": false,
        "hint": "External link to Planet Python",
        "urlaspattern": false,
        "hidden": false,
        "inbreadcrumbs": true,
        "access_perm_type": 1,
        "access_loggedin": false,
        "title": "Community News",
        "url": "http://planetpython.org/",
        "access_permissions": [],
        "inmenu": true,
        "insitetree": true,
        "sort_order": 144,
        "description": "",
        "alias": null,
        "access_guest": false,
        "parent": 142
    },
    "model": "sitetree.treeitem",
    "pk": 144
},
{
    "fields": {
        "tree": 2,
        "access_restricted": false,
        "hint": "External link to the PSF Blog",
        "urlaspattern": false,
        "hidden": false,
        "inbreadcrumbs": true,
        "access_perm_type": 1,
        "access_loggedin": false,
        "title": "PSF News",
        "url": "http://pyfound.blogspot.com/",
        "access_permissions": [],
        "inmenu": true,
        "insitetree": true,
        "sort_order": 145,
        "description": "",
        "alias": null,
        "access_guest": false,
        "parent": 142
    },
    "model": "sitetree.treeitem",
    "pk": 145
},
{
    "fields": {
        "tree": 2,
        "access_restricted": false,
        "hint": "External link to the PyCon blog",
        "urlaspattern": false,
        "hidden": false,
        "inbreadcrumbs": true,
        "access_perm_type": 1,
        "access_loggedin": false,
        "title": "PyCon News",
        "url": "http://pycon.blogspot.com/",
        "access_permissions": [],
        "inmenu": true,
        "insitetree": true,
        "sort_order": 146,
        "description": "",
        "alias": null,
        "access_guest": false,
        "parent": 142
    },
    "model": "sitetree.treeitem",
    "pk": 146
},
{
    "fields": {
        "tree": 2,
        "access_restricted": false,
        "hint": "",
        "urlaspattern": false,
        "hidden": false,
        "inbreadcrumbs": true,
        "access_perm_type": 1,
        "access_loggedin": false,
        "title": "Events",
        "url": "/events/",
        "access_permissions": [],
        "inmenu": true,
        "insitetree": true,
        "sort_order": 147,
        "description": "",
        "alias": null,
        "access_guest": false,
        "parent": 110
    },
    "model": "sitetree.treeitem",
    "pk": 147
},
{
    "fields": {
        "tree": 2,
        "access_restricted": false,
        "hint": "",
        "urlaspattern": false,
        "hidden": false,
        "inbreadcrumbs": true,
        "access_perm_type": 1,
        "access_loggedin": false,
        "title": "Python Events",
        "url": "/events/python-events/",
        "access_permissions": [],
        "inmenu": true,
        "insitetree": true,
        "sort_order": 149,
        "description": "",
        "alias": null,
        "access_guest": false,
        "parent": 147
    },
    "model": "sitetree.treeitem",
    "pk": 148
},
{
    "fields": {
        "tree": 2,
        "access_restricted": false,
        "hint": "",
        "urlaspattern": false,
        "hidden": false,
        "inbreadcrumbs": true,
        "access_perm_type": 1,
        "access_loggedin": false,
        "title": "User Group Events",
        "url": "/events/python-user-group/",
        "access_permissions": [],
        "inmenu": true,
        "insitetree": true,
        "sort_order": 151,
        "description": "",
        "alias": null,
        "access_guest": false,
        "parent": 147
    },
    "model": "sitetree.treeitem",
    "pk": 149
},
{
    "fields": {
        "tree": 2,
        "access_restricted": false,
        "hint": "",
        "urlaspattern": false,
        "hidden": false,
        "inbreadcrumbs": true,
        "access_perm_type": 1,
        "access_loggedin": false,
        "title": "Python Events Archive",
        "url": "/events/python-events/past/",
        "access_permissions": [],
        "inmenu": true,
        "insitetree": true,
        "sort_order": 150,
        "description": "",
        "alias": null,
        "access_guest": false,
        "parent": 147
    },
    "model": "sitetree.treeitem",
    "pk": 150
},
{
    "fields": {
        "tree": 2,
        "access_restricted": false,
        "hint": "",
        "urlaspattern": false,
        "hidden": false,
        "inbreadcrumbs": true,
        "access_perm_type": 1,
        "access_loggedin": false,
        "title": "User Group Events Archive",
        "url": "/events/python-user-group/past/",
        "access_permissions": [],
        "inmenu": true,
        "insitetree": true,
        "sort_order": 152,
        "description": "",
        "alias": null,
        "access_guest": false,
        "parent": 147
    },
    "model": "sitetree.treeitem",
    "pk": 151
},
{
    "fields": {
        "tree": 2,
        "access_restricted": false,
        "hint": "",
        "urlaspattern": false,
        "hidden": false,
        "inbreadcrumbs": true,
        "access_perm_type": 1,
        "access_loggedin": false,
        "title": "Submit an Event",
        "url": "https://wiki.python.org/moin/PythonEventsCalendar#Submitting_an_Event",
        "access_permissions": [],
        "inmenu": true,
        "insitetree": true,
        "sort_order": 153,
        "description": "",
        "alias": null,
        "access_guest": false,
        "parent": 147
    },
    "model": "sitetree.treeitem",
    "pk": 152
},
{
    "fields": {
        "tree": 2,
        "access_restricted": false,
        "hint": "",
        "urlaspattern": false,
        "hidden": false,
        "inbreadcrumbs": true,
        "access_perm_type": 1,
        "access_loggedin": false,
        "title": "Categories",
        "url": "/events/python-events/categories",
        "access_permissions": [],
        "inmenu": true,
        "insitetree": true,
        "sort_order": 148,
        "description": "",
        "alias": null,
        "access_guest": false,
        "parent": 147
    },
    "model": "sitetree.treeitem",
    "pk": 153
},
{
    "fields": {
        "tree": 2,
        "access_restricted": false,
        "hint": "",
        "urlaspattern": true,
        "hidden": false,
        "inbreadcrumbs": true,
        "access_perm_type": 1,
        "access_loggedin": false,
        "title": "Python Conferences",
        "url": "inner",
        "access_permissions": [],
        "inmenu": true,
        "insitetree": true,
        "sort_order": 154,
        "description": "",
        "alias": null,
        "access_guest": false,
        "parent": 147
    },
    "model": "sitetree.treeitem",
    "pk": 154
},
{
    "fields": {
        "tree": 2,
        "access_restricted": false,
        "hint": "",
        "urlaspattern": true,
        "hidden": false,
        "inbreadcrumbs": true,
        "access_perm_type": 1,
        "access_loggedin": false,
        "title": "Release Schedule",
        "url": "inner",
        "access_permissions": [],
        "inmenu": true,
        "insitetree": true,
        "sort_order": 155,
        "description": "",
        "alias": null,
        "access_guest": false,
        "parent": 147
    },
    "model": "sitetree.treeitem",
    "pk": 155
},
{
    "fields": {
        "tree": 2,
        "access_restricted": false,
        "hint": "",
        "urlaspattern": false,
        "hidden": false,
        "inbreadcrumbs": false,
        "access_perm_type": 1,
        "access_loggedin": false,
        "title": "Contributing",
        "url": "/dev/",
        "access_permissions": [],
        "inmenu": true,
        "insitetree": false,
        "sort_order": 156,
        "description": "",
        "alias": null,
        "access_guest": false,
        "parent": 110
    },
    "model": "sitetree.treeitem",
    "pk": 156
},
{
    "fields": {
        "tree": 2,
        "access_restricted": false,
        "hint": "",
        "urlaspattern": false,
        "hidden": false,
        "inbreadcrumbs": true,
        "access_perm_type": 1,
        "access_loggedin": false,
        "title": "Developer's Guide",
        "url": "http://docs.python.org/devguide/",
        "access_permissions": [],
        "inmenu": true,
        "insitetree": true,
        "sort_order": 157,
        "description": "",
        "alias": null,
        "access_guest": false,
        "parent": 156
    },
    "model": "sitetree.treeitem",
    "pk": 157
},
{
    "fields": {
        "tree": 2,
        "access_restricted": false,
        "hint": "",
        "urlaspattern": false,
        "hidden": false,
        "inbreadcrumbs": true,
        "access_perm_type": 1,
        "access_loggedin": false,
        "title": "Issue Tracker",
        "url": "http://bugs.python.org/",
        "access_permissions": [],
        "inmenu": true,
        "insitetree": true,
        "sort_order": 158,
        "description": "",
        "alias": null,
        "access_guest": false,
        "parent": 156
    },
    "model": "sitetree.treeitem",
    "pk": 158
},
{
    "fields": {
        "tree": 2,
        "access_restricted": false,
        "hint": "",
        "urlaspattern": false,
        "hidden": false,
        "inbreadcrumbs": true,
        "access_perm_type": 1,
        "access_loggedin": false,
        "title": "python-dev list",
        "url": "https://mail.python.org/mailman/listinfo/python-dev",
        "access_permissions": [],
        "inmenu": true,
        "insitetree": true,
        "sort_order": 159,
        "description": "",
        "alias": null,
        "access_guest": false,
        "parent": 156
    },
    "model": "sitetree.treeitem",
    "pk": 159
},
{
    "fields": {
        "tree": 2,
        "access_restricted": false,
        "hint": "",
        "urlaspattern": false,
        "hidden": false,
        "inbreadcrumbs": true,
        "access_perm_type": 1,
        "access_loggedin": false,
        "title": "Core Mentorship",
        "url": "http://pythonmentors.com/",
        "access_permissions": [],
        "inmenu": true,
        "insitetree": true,
        "sort_order": 160,
        "description": "",
        "alias": null,
        "access_guest": false,
        "parent": 156
    },
    "model": "sitetree.treeitem",
    "pk": 160
},
{
    "fields": {
        "tree": 2,
        "access_restricted": false,
        "hint": "",
        "urlaspattern": false,
        "hidden": false,
        "inbreadcrumbs": true,
        "access_perm_type": 1,
        "access_loggedin": false,
        "title": "Community",
        "url": "/community/",
        "access_permissions": [],
        "inmenu": true,
        "insitetree": true,
        "sort_order": 161,
        "description": "",
        "alias": null,
        "access_guest": false,
        "parent": null
    },
    "model": "sitetree.treeitem",
    "pk": 161
},
{
    "fields": {
        "tree": 2,
        "access_restricted": false,
        "hint": "",
        "urlaspattern": false,
        "hidden": false,
        "inbreadcrumbs": true,
        "access_perm_type": 1,
        "access_loggedin": false,
        "title": "Developers",
        "url": "/community/developers/",
        "access_permissions": [],
        "inmenu": true,
        "insitetree": true,
        "sort_order": 162,
        "description": "",
        "alias": null,
        "access_guest": false,
        "parent": 161
    },
    "model": "sitetree.treeitem",
    "pk": 162
},
{
    "fields": {
        "tree": 2,
        "access_restricted": false,
        "hint": "",
        "urlaspattern": false,
        "hidden": false,
        "inbreadcrumbs": true,
        "access_perm_type": 1,
        "access_loggedin": false,
        "title": "Membership",
        "url": "/community/membership",
        "access_permissions": [],
        "inmenu": true,
        "insitetree": true,
        "sort_order": 163,
        "description": "",
        "alias": null,
        "access_guest": false,
        "parent": 161
    },
    "model": "sitetree.treeitem",
    "pk": 163
},
{
    "fields": {
        "tree": 2,
        "access_restricted": false,
        "hint": "",
        "urlaspattern": false,
        "hidden": false,
        "inbreadcrumbs": true,
        "access_perm_type": 1,
        "access_loggedin": false,
        "title": "Education",
        "url": "/community/education",
        "access_permissions": [],
        "inmenu": true,
        "insitetree": true,
        "sort_order": 164,
        "description": "",
        "alias": null,
        "access_guest": false,
        "parent": 161
    },
    "model": "sitetree.treeitem",
    "pk": 164
},
{
    "fields": {
        "tree": 2,
        "access_restricted": false,
        "hint": "",
        "urlaspattern": false,
        "hidden": false,
        "inbreadcrumbs": true,
        "access_perm_type": 1,
        "access_loggedin": false,
        "title": "Community Awards",
        "url": "/community/awards",
        "access_permissions": [],
        "inmenu": true,
        "insitetree": true,
        "sort_order": 165,
        "description": "",
        "alias": null,
        "access_guest": false,
        "parent": 161
    },
    "model": "sitetree.treeitem",
    "pk": 165
},
{
    "fields": {
        "tree": 2,
        "access_restricted": false,
        "hint": "",
        "urlaspattern": true,
        "hidden": false,
        "inbreadcrumbs": true,
        "access_perm_type": 1,
        "access_loggedin": false,
        "title": "Foundation",
        "url": "psf-landing",
        "access_permissions": [],
        "inmenu": true,
        "insitetree": true,
        "sort_order": 166,
        "description": "",
        "alias": null,
        "access_guest": false,
        "parent": null
    },
    "model": "sitetree.treeitem",
    "pk": 166
},
{
    "fields": {
        "tree": 2,
        "access_restricted": false,
        "hint": "",
        "urlaspattern": false,
        "hidden": false,
        "inbreadcrumbs": true,
        "access_perm_type": 1,
        "access_loggedin": false,
        "title": "About",
        "url": "/psf/about",
        "access_permissions": [],
        "inmenu": true,
        "insitetree": true,
        "sort_order": 167,
        "description": "",
        "alias": null,
        "access_guest": false,
        "parent": 166
    },
    "model": "sitetree.treeitem",
    "pk": 167
},
{
    "fields": {
        "tree": 2,
        "access_restricted": false,
        "hint": "",
        "urlaspattern": false,
        "hidden": false,
        "inbreadcrumbs": true,
        "access_perm_type": 1,
        "access_loggedin": false,
        "title": "Executive Summary",
        "url": "/psf/summary",
        "access_permissions": [],
        "inmenu": true,
        "insitetree": true,
        "sort_order": 168,
        "description": "",
        "alias": null,
        "access_guest": false,
        "parent": 167
    },
    "model": "sitetree.treeitem",
    "pk": 168
},
{
    "fields": {
        "tree": 2,
        "access_restricted": false,
        "hint": "",
        "urlaspattern": false,
        "hidden": false,
        "inbreadcrumbs": true,
        "access_perm_type": 1,
        "access_loggedin": false,
        "title": "Mission statement",
        "url": "/psf/mission",
        "access_permissions": [],
        "inmenu": true,
        "insitetree": true,
        "sort_order": 169,
        "description": "",
        "alias": null,
        "access_guest": false,
        "parent": 167
    },
    "model": "sitetree.treeitem",
    "pk": 169
},
{
    "fields": {
        "tree": 2,
        "access_restricted": false,
        "hint": "",
        "urlaspattern": false,
        "hidden": false,
        "inbreadcrumbs": true,
        "access_perm_type": 1,
        "access_loggedin": false,
        "title": "Public records",
        "url": "/psf/records",
        "access_permissions": [],
        "inmenu": true,
        "insitetree": true,
        "sort_order": 170,
        "description": "",
        "alias": null,
        "access_guest": false,
        "parent": 167
    },
    "model": "sitetree.treeitem",
    "pk": 170
},
{
    "fields": {
        "tree": 2,
        "access_restricted": false,
        "hint": "",
        "urlaspattern": false,
        "hidden": false,
        "inbreadcrumbs": true,
        "access_perm_type": 1,
        "access_loggedin": false,
        "title": "Membership",
        "url": "/psf/membership",
        "access_permissions": [],
        "inmenu": true,
        "insitetree": true,
        "sort_order": 171,
        "description": "",
        "alias": null,
        "access_guest": false,
        "parent": 166
    },
    "model": "sitetree.treeitem",
    "pk": 171
},
{
    "fields": {
        "tree": 2,
        "access_restricted": false,
        "hint": "",
        "urlaspattern": false,
        "hidden": false,
        "inbreadcrumbs": true,
        "access_perm_type": 1,
        "access_loggedin": false,
        "title": "Sponsor Membership",
        "url": "/psf/sponsorship/",
        "access_permissions": [],
        "inmenu": true,
        "insitetree": true,
        "sort_order": 172,
        "description": "",
        "alias": null,
        "access_guest": false,
        "parent": 171
    },
    "model": "sitetree.treeitem",
    "pk": 172
},
{
    "fields": {
        "tree": 2,
        "access_restricted": false,
        "hint": "",
        "urlaspattern": false,
        "hidden": false,
        "inbreadcrumbs": true,
        "access_perm_type": 1,
        "access_loggedin": false,
        "title": "Membership FAQ",
        "url": "/psf/membership/",
        "access_permissions": [],
        "inmenu": true,
        "insitetree": true,
        "sort_order": 173,
        "description": "",
        "alias": null,
        "access_guest": false,
        "parent": 171
    },
    "model": "sitetree.treeitem",
    "pk": 173
},
{
    "fields": {
        "tree": 2,
        "access_restricted": false,
        "hint": "",
        "urlaspattern": false,
        "hidden": false,
        "inbreadcrumbs": true,
        "access_perm_type": 1,
        "access_loggedin": false,
        "title": "Membership roster",
        "url": "/psf/members/",
        "access_permissions": [],
        "inmenu": true,
        "insitetree": true,
        "sort_order": 174,
        "description": "",
        "alias": null,
        "access_guest": false,
        "parent": 171
    },
    "model": "sitetree.treeitem",
    "pk": 174
},
{
    "fields": {
        "tree": 2,
        "access_restricted": false,
        "hint": "",
        "urlaspattern": false,
        "hidden": false,
        "inbreadcrumbs": true,
        "access_perm_type": 1,
        "access_loggedin": false,
        "title": "League",
        "url": "/psf/league/",
        "access_permissions": [],
        "inmenu": true,
        "insitetree": true,
        "sort_order": 175,
        "description": "",
        "alias": null,
        "access_guest": false,
        "parent": 171
    },
    "model": "sitetree.treeitem",
    "pk": 175
},
{
    "fields": {
        "tree": 2,
        "access_restricted": false,
        "hint": "",
        "urlaspattern": false,
        "hidden": false,
        "inbreadcrumbs": true,
        "access_perm_type": 1,
        "access_loggedin": false,
        "title": "Sign up as member",
        "url": "/users/membership/",
        "access_permissions": [],
        "inmenu": true,
        "insitetree": true,
        "sort_order": 176,
        "description": "",
        "alias": null,
        "access_guest": false,
        "parent": 171
    },
    "model": "sitetree.treeitem",
    "pk": 176
},
{
    "fields": {
        "tree": 2,
        "access_restricted": false,
        "hint": "",
        "urlaspattern": false,
        "hidden": false,
        "inbreadcrumbs": true,
        "access_perm_type": 1,
        "access_loggedin": false,
        "title": "Self-certify as voting member",
        "url": "http://pyfound.blogspot.de/2015/02/enroll-as-psf-voting-member.html",
        "access_permissions": [],
        "inmenu": true,
        "insitetree": true,
        "sort_order": 177,
        "description": "",
        "alias": null,
        "access_guest": false,
        "parent": 171
    },
    "model": "sitetree.treeitem",
    "pk": 177
},
{
    "fields": {
        "tree": 2,
        "access_restricted": false,
        "hint": "",
        "urlaspattern": false,
        "hidden": false,
        "inbreadcrumbs": true,
        "access_perm_type": 1,
        "access_loggedin": false,
        "title": "Python Community Code of Conduct",
        "url": "/psf/codeofconduct/",
        "access_permissions": [],
        "inmenu": true,
        "insitetree": true,
        "sort_order": 178,
        "description": "",
        "alias": null,
        "access_guest": false,
        "parent": 171
    },
    "model": "sitetree.treeitem",
    "pk": 178
},
{
    "fields": {
        "tree": 2,
        "access_restricted": false,
        "hint": "",
        "urlaspattern": false,
        "hidden": false,
        "inbreadcrumbs": true,
        "access_perm_type": 1,
        "access_loggedin": false,
        "title": "Donations",
        "url": "/psf/donations",
        "access_permissions": [],
        "inmenu": true,
        "insitetree": true,
        "sort_order": 179,
        "description": "",
        "alias": null,
        "access_guest": false,
        "parent": 166
    },
    "model": "sitetree.treeitem",
    "pk": 179
},
{
    "fields": {
        "tree": 2,
        "access_restricted": false,
        "hint": "",
        "urlaspattern": false,
        "hidden": false,
        "inbreadcrumbs": true,
        "access_perm_type": 1,
        "access_loggedin": false,
        "title": "Volunteer",
        "url": "/psf/volunteer/",
        "access_permissions": [],
        "inmenu": true,
        "insitetree": true,
        "sort_order": 180,
        "description": "",
        "alias": null,
        "access_guest": false,
        "parent": 179
    },
    "model": "sitetree.treeitem",
    "pk": 180
},
{
    "fields": {
        "tree": 2,
        "access_restricted": false,
        "hint": "",
        "urlaspattern": false,
        "hidden": false,
        "inbreadcrumbs": true,
        "access_perm_type": 1,
        "access_loggedin": false,
        "title": "Contribution forms",
        "url": "/psf/contrib/",
        "access_permissions": [],
        "inmenu": true,
        "insitetree": true,
        "sort_order": 181,
        "description": "",
        "alias": null,
        "access_guest": false,
        "parent": 179
    },
    "model": "sitetree.treeitem",
    "pk": 181
},
{
    "fields": {
        "tree": 2,
        "access_restricted": false,
        "hint": "",
        "urlaspattern": false,
        "hidden": false,
        "inbreadcrumbs": true,
        "access_perm_type": 1,
        "access_loggedin": false,
        "title": "Grants program",
        "url": "/psf/grants/",
        "access_permissions": [],
        "inmenu": true,
        "insitetree": true,
        "sort_order": 182,
        "description": "",
        "alias": null,
        "access_guest": false,
        "parent": 179
    },
    "model": "sitetree.treeitem",
    "pk": 182
},
{
    "fields": {
        "tree": 2,
        "access_restricted": false,
        "hint": "",
        "urlaspattern": false,
        "hidden": false,
        "inbreadcrumbs": true,
        "access_perm_type": 1,
        "access_loggedin": false,
        "title": "Suspicious checks",
        "url": "/psf/fraud/",
        "access_permissions": [],
        "inmenu": true,
        "insitetree": true,
        "sort_order": 183,
        "description": "",
        "alias": null,
        "access_guest": false,
        "parent": 179
    },
    "model": "sitetree.treeitem",
    "pk": 183
},
{
    "fields": {
        "tree": 2,
        "access_restricted": false,
        "hint": "",
        "urlaspattern": false,
        "hidden": false,
        "inbreadcrumbs": true,
        "access_perm_type": 1,
        "access_loggedin": false,
        "title": "Legal",
        "url": "/about/legal/",
        "access_permissions": [],
        "inmenu": true,
        "insitetree": true,
        "sort_order": 184,
        "description": "",
        "alias": null,
        "access_guest": false,
        "parent": 166
    },
    "model": "sitetree.treeitem",
    "pk": 184
},
{
    "fields": {
        "tree": 2,
        "access_restricted": false,
        "hint": "",
        "urlaspattern": false,
        "hidden": false,
        "inbreadcrumbs": true,
        "access_perm_type": 1,
        "access_loggedin": false,
        "title": "Bylaws",
        "url": "/psf/bylaws/",
        "access_permissions": [],
        "inmenu": true,
        "insitetree": true,
        "sort_order": 185,
        "description": "",
        "alias": null,
        "access_guest": false,
        "parent": 184
    },
    "model": "sitetree.treeitem",
    "pk": 185
},
{
    "fields": {
        "tree": 2,
        "access_restricted": false,
        "hint": "",
        "urlaspattern": false,
        "hidden": false,
        "inbreadcrumbs": true,
        "access_perm_type": 1,
        "access_loggedin": false,
        "title": "Trademark policy",
        "url": "/psf/trademarks/",
        "access_permissions": [],
        "inmenu": true,
        "insitetree": true,
        "sort_order": 186,
        "description": "",
        "alias": null,
        "access_guest": false,
        "parent": 184
    },
    "model": "sitetree.treeitem",
    "pk": 186
},
{
    "fields": {
        "tree": 2,
        "access_restricted": false,
        "hint": "",
        "urlaspattern": false,
        "hidden": false,
        "inbreadcrumbs": true,
        "access_perm_type": 1,
        "access_loggedin": false,
        "title": " PyCon Trademark Policy",
        "url": "/psf/trademarks/pycon/",
        "access_permissions": [],
        "inmenu": true,
        "insitetree": true,
        "sort_order": 187,
        "description": "",
        "alias": null,
        "access_guest": false,
        "parent": 186
    },
    "model": "sitetree.treeitem",
    "pk": 187
},
{
    "fields": {
        "tree": 2,
        "access_restricted": false,
        "hint": "",
        "urlaspattern": false,
        "hidden": false,
        "inbreadcrumbs": true,
        "access_perm_type": 1,
        "access_loggedin": false,
        "title": "Weblog policy",
        "url": "/psf/weblog-policy",
        "access_permissions": [],
        "inmenu": true,
        "insitetree": true,
        "sort_order": 188,
        "description": "",
        "alias": null,
        "access_guest": false,
        "parent": 184
    },
    "model": "sitetree.treeitem",
    "pk": 188
},
{
    "fields": {
        "tree": 2,
        "access_restricted": false,
        "hint": "",
        "urlaspattern": false,
        "hidden": false,
        "inbreadcrumbs": true,
        "access_perm_type": 1,
        "access_loggedin": false,
        "title": "License",
        "url": "/psf/license",
        "access_permissions": [],
        "inmenu": true,
        "insitetree": true,
        "sort_order": 189,
        "description": "",
        "alias": null,
        "access_guest": false,
        "parent": 184
    },
    "model": "sitetree.treeitem",
    "pk": 189
},
{
    "fields": {
        "tree": 2,
        "access_restricted": false,
        "hint": "",
        "urlaspattern": true,
        "hidden": false,
        "inbreadcrumbs": true,
        "access_perm_type": 1,
        "access_loggedin": false,
        "title": "Media",
        "url": "inner",
        "access_permissions": [],
        "inmenu": true,
        "insitetree": true,
        "sort_order": 190,
        "description": "",
        "alias": null,
        "access_guest": false,
        "parent": 166
    },
    "model": "sitetree.treeitem",
    "pk": 190
},
{
    "fields": {
        "tree": 2,
        "access_restricted": false,
        "hint": "",
        "urlaspattern": false,
        "hidden": false,
        "inbreadcrumbs": true,
        "access_perm_type": 1,
        "access_loggedin": false,
        "title": "Press releases",
        "url": "/psf/press-release/",
        "access_permissions": [],
        "inmenu": true,
        "insitetree": true,
        "sort_order": 191,
        "description": "",
        "alias": null,
        "access_guest": false,
        "parent": 190
    },
    "model": "sitetree.treeitem",
    "pk": 191
},
{
    "fields": {
        "tree": 2,
        "access_restricted": false,
        "hint": "",
        "urlaspattern": false,
        "hidden": false,
        "inbreadcrumbs": true,
        "access_perm_type": 1,
        "access_loggedin": false,
        "title": "Awards",
        "url": "/community/awards/",
        "access_permissions": [],
        "inmenu": true,
        "insitetree": true,
        "sort_order": 192,
        "description": "",
        "alias": null,
        "access_guest": false,
        "parent": 190
    },
    "model": "sitetree.treeitem",
    "pk": 192
},
{
    "fields": {
        "tree": 2,
        "access_restricted": false,
        "hint": "",
        "urlaspattern": false,
        "hidden": false,
        "inbreadcrumbs": true,
        "access_perm_type": 1,
        "access_loggedin": false,
        "title": "Logo",
        "url": "/community/logos/",
        "access_permissions": [],
        "inmenu": true,
        "insitetree": true,
        "sort_order": 193,
        "description": "",
        "alias": null,
        "access_guest": false,
        "parent": 190
    },
    "model": "sitetree.treeitem",
    "pk": 193
},
{
    "fields": {
        "tree": 2,
        "access_restricted": false,
        "hint": "",
        "urlaspattern": false,
        "hidden": false,
        "inbreadcrumbs": true,
        "access_perm_type": 1,
        "access_loggedin": false,
        "title": "PSF News",
        "url": "http://pyfound.blogspot.com/",
        "access_permissions": [],
        "inmenu": true,
        "insitetree": true,
        "sort_order": 194,
        "description": "",
        "alias": null,
        "access_guest": false,
        "parent": 166
    },
    "model": "sitetree.treeitem",
    "pk": 194
},
{
    "fields": {
        "tree": 2,
        "access_restricted": false,
        "hint": "",
        "urlaspattern": false,
        "hidden": false,
        "inbreadcrumbs": true,
        "access_perm_type": 1,
        "access_loggedin": false,
        "title": "Docs",
        "url": "https://docs.python.org",
        "access_permissions": [],
        "inmenu": true,
        "insitetree": true,
        "sort_order": 195,
        "description": "",
        "alias": null,
        "access_guest": false,
        "parent": null
    },
    "model": "sitetree.treeitem",
    "pk": 195
},
{
    "fields": {
        "tree": 2,
        "access_restricted": false,
        "hint": "",
        "urlaspattern": false,
        "hidden": false,
        "inbreadcrumbs": true,
        "access_perm_type": 1,
        "access_loggedin": false,
        "title": "Python 2.7 (stable)",
        "url": "https://docs.python.org/2.7/",
        "access_permissions": [],
        "inmenu": true,
        "insitetree": true,
        "sort_order": 196,
        "description": "",
        "alias": null,
        "access_guest": false,
        "parent": 195
    },
    "model": "sitetree.treeitem",
    "pk": 196
},
{
    "fields": {
        "tree": 2,
        "access_restricted": false,
        "hint": "",
        "urlaspattern": false,
        "hidden": false,
        "inbreadcrumbs": true,
        "access_perm_type": 1,
        "access_loggedin": false,
        "title": "Python 3.3 (stable)",
        "url": "https://docs.python.org/3.3/",
        "access_permissions": [],
        "inmenu": true,
        "insitetree": true,
        "sort_order": 197,
        "description": "",
        "alias": null,
        "access_guest": false,
        "parent": 195
    },
    "model": "sitetree.treeitem",
    "pk": 197
},
{
    "fields": {
        "tree": 2,
        "access_restricted": false,
        "hint": "",
        "urlaspattern": false,
        "hidden": false,
        "inbreadcrumbs": true,
        "access_perm_type": 1,
        "access_loggedin": false,
        "title": "Python 3.5 (development)",
        "url": "https://docs.python.org/3.5/",
        "access_permissions": [],
        "inmenu": true,
        "insitetree": true,
        "sort_order": 198,
        "description": "",
        "alias": null,
        "access_guest": false,
        "parent": 195
    },
    "model": "sitetree.treeitem",
    "pk": 198
},
{
    "fields": {
        "tree": 2,
        "access_restricted": false,
        "hint": "",
        "urlaspattern": false,
        "hidden": false,
        "inbreadcrumbs": true,
        "access_perm_type": 1,
        "access_loggedin": false,
        "title": "Old Versions",
        "url": "https://www.python.org/doc/versions/",
        "access_permissions": [],
        "inmenu": true,
        "insitetree": true,
        "sort_order": 199,
        "description": "",
        "alias": null,
        "access_guest": false,
        "parent": 195
    },
    "model": "sitetree.treeitem",
    "pk": 199
},
{
    "fields": {
        "tree": 2,
        "access_restricted": false,
        "hint": "",
        "urlaspattern": false,
        "hidden": false,
        "inbreadcrumbs": true,
        "access_perm_type": 1,
        "access_loggedin": false,
        "title": "Download Docs",
        "url": "https://docs.python.org/3/download.html",
        "access_permissions": [],
        "inmenu": true,
        "insitetree": true,
        "sort_order": 200,
        "description": "",
        "alias": null,
        "access_guest": false,
        "parent": 195
    },
    "model": "sitetree.treeitem",
    "pk": 200
},
{
    "fields": {
        "tree": 2,
        "access_restricted": false,
        "hint": "",
        "urlaspattern": false,
        "hidden": false,
        "inbreadcrumbs": true,
        "access_perm_type": 1,
        "access_loggedin": false,
        "title": "PyPI",
        "url": "https://pypi.python.org/pypi",
        "access_permissions": [],
        "inmenu": true,
        "insitetree": true,
        "sort_order": 201,
        "description": "",
        "alias": null,
        "access_guest": false,
        "parent": null
    },
    "model": "sitetree.treeitem",
    "pk": 201
},
{
    "fields": {
        "tree": 2,
        "access_restricted": false,
        "hint": "",
        "urlaspattern": false,
        "hidden": false,
        "inbreadcrumbs": true,
        "access_perm_type": 1,
        "access_loggedin": false,
        "title": "Browse Packages",
        "url": "https://pypi.python.org/pypi?%3Aaction=browse",
        "access_permissions": [],
        "inmenu": true,
        "insitetree": true,
        "sort_order": 202,
        "description": "",
        "alias": null,
        "access_guest": false,
        "parent": 201
    },
    "model": "sitetree.treeitem",
    "pk": 202
},
{
    "fields": {
        "tree": 2,
        "access_restricted": false,
        "hint": "",
        "urlaspattern": false,
        "hidden": false,
        "inbreadcrumbs": true,
        "access_perm_type": 1,
        "access_loggedin": false,
        "title": "Package Submission",
        "url": "https://pypi.python.org/pypi?%3Aaction=submit_form",
        "access_permissions": [],
        "inmenu": true,
        "insitetree": true,
        "sort_order": 203,
        "description": "",
        "alias": null,
        "access_guest": false,
        "parent": 201
    },
    "model": "sitetree.treeitem",
    "pk": 203
},
{
    "fields": {
        "tree": 2,
        "access_restricted": false,
        "hint": "",
        "urlaspattern": false,
        "hidden": false,
        "inbreadcrumbs": true,
        "access_perm_type": 1,
        "access_loggedin": false,
        "title": "List trove classifiers",
        "url": "https://pypi.python.org/pypi?%3Aaction=list_classifiers",
        "access_permissions": [],
        "inmenu": true,
        "insitetree": true,
        "sort_order": 204,
        "description": "",
        "alias": null,
        "access_guest": false,
        "parent": 201
    },
    "model": "sitetree.treeitem",
    "pk": 204
},
{
    "fields": {
        "tree": 2,
        "access_restricted": false,
        "hint": "",
        "urlaspattern": false,
        "hidden": false,
        "inbreadcrumbs": true,
        "access_perm_type": 1,
        "access_loggedin": false,
        "title": "List packages",
        "url": "https://pypi.python.org/pypi?%3Aaction=index",
        "access_permissions": [],
        "inmenu": true,
        "insitetree": true,
        "sort_order": 205,
        "description": "",
        "alias": null,
        "access_guest": false,
        "parent": 201
    },
    "model": "sitetree.treeitem",
    "pk": 205
},
{
    "fields": {
        "tree": 2,
        "access_restricted": false,
        "hint": "",
        "urlaspattern": false,
        "hidden": false,
        "inbreadcrumbs": true,
        "access_perm_type": 1,
        "access_loggedin": false,
        "title": "Python 3 packages",
        "url": "https://pypi.python.org/pypi?:action=browse&c=533&show=all",
        "access_permissions": [],
        "inmenu": true,
        "insitetree": true,
        "sort_order": 206,
        "description": "",
        "alias": null,
        "access_guest": false,
        "parent": 201
    },
    "model": "sitetree.treeitem",
    "pk": 206
},
{
    "fields": {
        "tree": 2,
        "access_restricted": false,
        "hint": "",
        "urlaspattern": false,
        "hidden": false,
        "inbreadcrumbs": true,
        "access_perm_type": 1,
        "access_loggedin": false,
        "title": "Jobs",
        "url": "https://www.python.org/jobs/",
        "access_permissions": [],
        "inmenu": true,
        "insitetree": true,
        "sort_order": 207,
        "description": "",
        "alias": null,
        "access_guest": false,
        "parent": null
    },
    "model": "sitetree.treeitem",
    "pk": 207
},
{
    "fields": {
        "tree": 2,
        "access_restricted": false,
        "hint": "",
        "urlaspattern": false,
        "hidden": false,
        "inbreadcrumbs": true,
        "access_perm_type": 1,
        "access_loggedin": false,
        "title": "Browse Jobs",
        "url": "https://www.python.org/jobs/",
        "access_permissions": [],
        "inmenu": true,
        "insitetree": true,
        "sort_order": 208,
        "description": "",
        "alias": null,
        "access_guest": false,
        "parent": 207
    },
    "model": "sitetree.treeitem",
    "pk": 208
},
{
    "fields": {
        "tree": 2,
        "access_restricted": false,
        "hint": "",
        "urlaspattern": false,
        "hidden": false,
        "inbreadcrumbs": true,
        "access_perm_type": 1,
        "access_loggedin": false,
        "title": "Locations",
        "url": "https://www.python.org/jobs/locations/",
        "access_permissions": [],
        "inmenu": true,
        "insitetree": true,
        "sort_order": 209,
        "description": "",
        "alias": null,
        "access_guest": false,
        "parent": 207
    },
    "model": "sitetree.treeitem",
    "pk": 209
},
{
    "fields": {
        "tree": 2,
        "access_restricted": false,
        "hint": "",
        "urlaspattern": false,
        "hidden": false,
        "inbreadcrumbs": true,
        "access_perm_type": 1,
        "access_loggedin": false,
        "title": "Categories",
        "url": "https://www.python.org/jobs/categories/",
        "access_permissions": [],
        "inmenu": true,
        "insitetree": true,
        "sort_order": 210,
        "description": "",
        "alias": null,
        "access_guest": false,
        "parent": 207
    },
    "model": "sitetree.treeitem",
    "pk": 210
},
{
    "fields": {
        "tree": 2,
        "access_restricted": false,
        "hint": "",
        "urlaspattern": false,
        "hidden": false,
        "inbreadcrumbs": true,
        "access_perm_type": 1,
        "access_loggedin": false,
        "title": "Data Analyst",
        "url": "https://www.python.org/jobs/category/data-analyst/",
        "access_permissions": [],
        "inmenu": true,
        "insitetree": true,
        "sort_order": 211,
        "description": "",
        "alias": null,
        "access_guest": false,
        "parent": 210
    },
    "model": "sitetree.treeitem",
    "pk": 211
},
{
    "fields": {
        "tree": 2,
        "access_restricted": false,
        "hint": "",
        "urlaspattern": false,
        "hidden": false,
        "inbreadcrumbs": true,
        "access_perm_type": 1,
        "access_loggedin": false,
        "title": "Developer / Engineer",
        "url": "https://www.python.org/jobs/category/developer-engineer/",
        "access_permissions": [],
        "inmenu": true,
        "insitetree": true,
        "sort_order": 212,
        "description": "",
        "alias": null,
        "access_guest": false,
        "parent": 210
    },
    "model": "sitetree.treeitem",
    "pk": 212
},
{
    "fields": {
        "tree": 2,
        "access_restricted": false,
        "hint": "",
        "urlaspattern": false,
        "hidden": false,
        "inbreadcrumbs": true,
        "access_perm_type": 1,
        "access_loggedin": false,
        "title": "Researcher / Scientist",
        "url": "https://www.python.org/jobs/category/researcher-scientist/",
        "access_permissions": [],
        "inmenu": true,
        "insitetree": true,
        "sort_order": 213,
        "description": "",
        "alias": null,
        "access_guest": false,
        "parent": 210
    },
    "model": "sitetree.treeitem",
    "pk": 213
},
{
    "fields": {
        "tree": 2,
        "access_restricted": false,
        "hint": "",
        "urlaspattern": false,
        "hidden": false,
        "inbreadcrumbs": true,
        "access_perm_type": 1,
        "access_loggedin": false,
        "title": "Software Engineer",
        "url": "https://www.python.org/jobs/category/software-engineer/",
        "access_permissions": [],
        "inmenu": true,
        "insitetree": true,
        "sort_order": 214,
        "description": "",
        "alias": null,
        "access_guest": false,
        "parent": 210
    },
    "model": "sitetree.treeitem",
    "pk": 214
},
{
    "fields": {
        "tree": 2,
        "access_restricted": false,
        "hint": "",
        "urlaspattern": false,
        "hidden": false,
        "inbreadcrumbs": true,
        "access_perm_type": 1,
        "access_loggedin": false,
        "title": "Other",
        "url": "https://www.python.org/jobs/category/other/",
        "access_permissions": [],
        "inmenu": true,
        "insitetree": true,
        "sort_order": 215,
        "description": "",
        "alias": null,
        "access_guest": false,
        "parent": 210
    },
    "model": "sitetree.treeitem",
    "pk": 215
},
{
    "fields": {
        "tree": 2,
        "access_restricted": false,
        "hint": "",
        "urlaspattern": false,
        "hidden": false,
        "inbreadcrumbs": true,
        "access_perm_type": 1,
        "access_loggedin": false,
        "title": "Submit a Job (Log in)",
        "url": "https://www.python.org/accounts/login/?next=/jobs/create/",
        "access_permissions": [],
        "inmenu": true,
        "insitetree": true,
        "sort_order": 217,
        "description": "",
        "alias": null,
        "access_guest": false,
        "parent": 207
    },
    "model": "sitetree.treeitem",
    "pk": 216
},
{
    "fields": {
        "tree": 2,
        "access_restricted": false,
        "hint": "",
        "urlaspattern": false,
        "hidden": false,
        "inbreadcrumbs": true,
        "access_perm_type": 1,
        "access_loggedin": false,
        "title": "Manage My Jobs (Log in)",
        "url": "https://www.python.org/accounts/login/?next=/jobs/mine/",
        "access_permissions": [],
        "inmenu": true,
        "insitetree": true,
        "sort_order": 218,
        "description": "",
        "alias": null,
        "access_guest": false,
        "parent": 207
    },
    "model": "sitetree.treeitem",
    "pk": 217
},
{
    "fields": {
        "tree": 2,
        "access_restricted": false,
        "hint": "",
        "urlaspattern": false,
        "hidden": false,
        "inbreadcrumbs": true,
        "access_perm_type": 1,
        "access_loggedin": false,
        "title": "Technology  Types",
        "url": "https://www.python.org/jobs/types/",
        "access_permissions": [],
        "inmenu": true,
        "insitetree": true,
        "sort_order": 216,
        "description": "",
        "alias": null,
        "access_guest": false,
        "parent": 207
    },
    "model": "sitetree.treeitem",
    "pk": 218
},
{
    "fields": {
        "tree": 2,
        "access_restricted": false,
        "hint": "",
        "urlaspattern": false,
        "hidden": false,
        "inbreadcrumbs": true,
        "access_perm_type": 1,
        "access_loggedin": false,
        "title": "Jobs RSS",
        "url": "https://www.python.org/jobs/feed/rss/",
        "access_permissions": [],
        "inmenu": true,
        "insitetree": true,
        "sort_order": 219,
        "description": "",
        "alias": null,
        "access_guest": false,
        "parent": 207
    },
    "model": "sitetree.treeitem",
    "pk": 219
}
]
